borec_tool/__init__.py
borec_tool/__main__.py
borec_tool/bands_browser_with_graph.py
borec_tool/borec_tool.py
borec_tool/clustering.py
borec_tool/img_pca.py
borec_tool/img_quantiles.py
borec_tool/img_sigma.py
borec_tool/img_widget.py
borec_tool/led_lighting.py
borec_tool/led_spectra.py
borec_tool/radiance.py
borec_tool/save.py
borec_tool/spectrum_window.py
borec_tool/tab_widget.py
borec_tool/data_utilities/__init__.py
borec_tool/data_utilities/cube.py
borec_tool/data_utilities/loader.py
borec_tool/data_utilities/saver.py
borec_tool/data_utilities/statistics.py
borec_tool/gui/__init__.py
borec_tool/gui/about-widget.py
borec_tool/gui/band_slider.py
borec_tool/gui/imshow_widget.py
borec_tool/gui/multidirdialog.py
borec_tool/gui/ndarray2pixmap.py
borec_tool/gui/param_box.py
borec_tool/gui/parameters.py
borec_tool/gui/scene.py
borec_tool/gui/selection.py
borec_tool/gui/viewer.py
borec_tool/processing/__init__.py
borec_tool/processing/algorithms.py
borec_tool/processing/bilateral.py
borec_tool/processing/pca_dbscan.py
borec_tool/processing/pca_kmeans.py
borec_tool/processing/process_bezier_svg.py
borec_tool/processing/reflectance.py
borec_tool/resources/__init__.py
borec_tool/resources/graph.yaml
borec_tool/resources/xyzbar_interpolated.mat
borec_tool/resources/CAMEA-LED/EP2012-350IR4.svg
borec_tool/resources/CAMEA-LED/EP2016-350IR4.svg
borec_tool/resources/CAMEA-LED/EP201C-350IR4.svg
borec_tool/resources/CAMEA-LED/EP201K-350IR4.svg
borec_tool/resources/CAMEA-LED/EP503IR4L017W.svg
borec_tool/resources/CAMEA-LED/EP505L-350Y1.svg
borec_tool/resources/CAMEA-LED/L760-AU-03AU.svg
borec_tool/resources/CAMEA-LED/SFH4258-Z.svg
borec_tool/resources/CAMEA-LED/SFH4550.svg
borec_tool/resources/CAMEA-LED/SFH4715S.svg
borec_tool/resources/CAMEA-LED/SFH4780S.svg
borec_tool/resources/CAMEA-LED/SFH4787S.svg
borec_tool/resources/CAMEA-LED/SMBB1050D-1100-02.svg
borec_tool/resources/CAMEA-LED/SMBB590D-1100-02.svg
borec_tool/resources/CAMEA-LED/SMBB620D-1100-02.svg
borec_tool-2020.3.dist-info/LICENCE.txt
borec_tool-2020.3.dist-info/METADATA
borec_tool-2020.3.dist-info/WHEEL
borec_tool-2020.3.dist-info/top_level.txt
borec_tool-2020.3.dist-info/RECORD
