Metadata-Version: 2.1
Name: borec-tool
Version: 2020.3
Summary: Tool for visualization and analysis of hyperspectral data
Home-page: https://gita.utia.cas.cz/schier/borec-tool.git
Author: Jan Schier
Author-email: schier@utia.cas.cz
License: BSD 3-Clause License
Project-URL: Repository, https://gita.utia.cas.cz/schier/borec-tool.git
Platform: UNKNOWN
Classifier: Development Status :: 4 - Beta
Classifier: Intended Audience :: Science/Research
Classifier: Topic :: Scientific/Engineering :: Image Processing
Classifier: License :: OSI Approved :: BSD License
Classifier: Programming Language :: Python :: 3.7
Classifier: Programming Language :: Python :: 3.8
Classifier: Programming Language :: Python :: 3.9
Classifier: Operating System :: OS Independent
Requires-Dist: pyqt5
Requires-Dist: matplotlib
Requires-Dist: numpy
Requires-Dist: scipy
Requires-Dist: pandas
Requires-Dist: scikit-learn
Requires-Dist: seaborn
Requires-Dist: scikit-image
Requires-Dist: hdbscan
Requires-Dist: svgpathtools
Requires-Dist: setuptools
Requires-Dist: spectral
Requires-Dist: beautifulsoup4
Requires-Dist: imageio
Requires-Dist: pyyaml
